evernetpy/__init__.py
evernetpy/client.py
evernetpy/criteria.py
evernetpy/execute.py
evernetpy/lookups.py
evernetpy/memoize.py
evernetpy/parser.py
evernetpy/query.py
evernetpy-5.0.0.dist-info/DESCRIPTION.rst
evernetpy-5.0.0.dist-info/METADATA
evernetpy-5.0.0.dist-info/metadata.json
evernetpy-5.0.0.dist-info/RECORD
evernetpy-5.0.0.dist-info/top_level.txt
evernetpy-5.0.0.dist-info/WHEEL
