Metadata-Version: 2.0
Name: evernetpy
Version: 5.0.0
Summary: A Python library for interacting with the EverNet listing service
Home-page: https://github.com/RealGeeks/evernetpy
Author: Kevin McCarthy
Author-email: me@kevinmccarthy.org
License: MIT
Platform: UNKNOWN
Classifier: Environment :: Console
Classifier: Intended Audience :: Developers
Classifier: Programming Language :: Python
Classifier: License :: OSI Approved :: MIT License
Requires-Dist: requests
